stopwatch/__init__.py
stpwch-0.0.2.dist-info/METADATA
stpwch-0.0.2.dist-info/WHEEL
stpwch-0.0.2.dist-info/top_level.txt
stpwch-0.0.2.dist-info/RECORD
