Metadata-Version: 2.1
Name: stpwch
Version: 0.0.2
Summary: An insanely simple stop watch library
Home-page: http://github.com/Ehnryu/stopwatch
Author: Ehnryu/Sakurai07
Author-email: blzzardst0rm@gmail.com
License: MIT
Keywords: stopwatch,tasks,time
Platform: UNKNOWN
